sage_newsletter/__init__.py
sage_newsletter/actions/__init__.py
sage_newsletter/actions/newsletter.py
sage_newsletter/admin.py
sage_newsletter/apps.py
sage_newsletter/forms.py
sage_newsletter/helpers/__init__.py
sage_newsletter/helpers/text_choices.py
sage_newsletter/locale/ar/LC_MESSAGES/django.po
sage_newsletter/locale/en/LC_MESSAGES/django.po
sage_newsletter/locale/fa/LC_MESSAGES/django.po
sage_newsletter/migrations/0001_initial.py
sage_newsletter/migrations/__init__.py
sage_newsletter/models.py
sage_newsletter/tests/__init__.py
sage_newsletter/tests/test_action.py
sage_newsletter/tests/test_form.py
sage_newsletter/tests/test_view.py
sage_newsletter/views.py
django_sage_newsletter-0.1.4.dist-info/LICENSE
django_sage_newsletter-0.1.4.dist-info/METADATA
django_sage_newsletter-0.1.4.dist-info/WHEEL
django_sage_newsletter-0.1.4.dist-info/RECORD
