Metadata-Version: 2.1
Name: django-sage-newsletter
Version: 0.1.4
Summary: Comprehensive package to handle newsletter emails.
Home-page: https://github.com/sageteamorg/django-sage-newsletter
License: MIT
Keywords: django,email marketing,newsletter
Author: Sepehr Akbarzadeh
Author-email: sepehr@sageteam.org
Requires-Python: >=3.10,<4.0
Classifier: Environment :: Web Environment
Classifier: Framework :: Django
Classifier: Framework :: Django :: 4.2
Classifier: Framework :: Django :: 5.0
Classifier: Framework :: Django :: 5.1
Classifier: License :: OSI Approved :: MIT License
Classifier: Operating System :: OS Independent
Classifier: Programming Language :: Python
Classifier: Programming Language :: Python :: 3
Classifier: Programming Language :: Python :: 3.10
Classifier: Programming Language :: Python :: 3.11
Classifier: Programming Language :: Python :: 3.12
Classifier: Programming Language :: Python :: 3 :: Only
Requires-Dist: django (>=4.2,<5.0) ; python_version == "3.10"
Requires-Dist: django (>=4.2,<5.3) ; python_version >= "3.10"
Project-URL: Issues, https://github.com/sageteamorg/django-sage-newsletter/issues
Project-URL: Repository, https://github.com/sageteamorg/django-sage-newsletter
Project-URL: Source Code, https://github.com/sageteamorg/django-sage-newsletter
